{
  "north_america": {
    "region": "north_america",
    "latitude": 40.7128,
    "longitude": -74.006,
    "star_data_by_hour": {
      "2026-03-27T19:00:00": [],
      "2026-03-27T20:00:00": [],
      "2026-03-27T21:00:00": [],
      "2026-03-27T22:00:00": [],
      "2026-03-27T23:00:00": [],
      "2026-03-28T00:00:00": [],
      "2026-03-28T01:00:00": [],
      "2026-03-28T02:00:00": [],
      "2026-03-28T03:00:00": [],
      "2026-03-28T04:00:00": [],
      "2026-03-28T05:00:00": [],
      "2026-03-28T06:00:00": [],
      "2026-03-28T07:00:00": [],
      "2026-03-28T08:00:00": [],
      "2026-03-28T09:00:00": [
        {
          "star_name": "Vega",
          "altitude_degrees": 64.96117330392234,
          "azimuth_degrees": 83.62234209095108,
          "distance_au": 206264806247096.97
        }
      ],
      "2026-03-28T10:00:00": [
        {
          "star_name": "Vega",
          "altitude_degrees": 76.34159627786708,
          "azimuth_degrees": 92.3112383231527,
          "distance_au": 206264806247097.03
        }
      ],
      "2026-03-28T11:00:00": [
        {
          "star_name": "Vega",
          "altitude_degrees": 87.2439448724878,
          "azimuth_degrees": 133.11268991374016,
          "distance_au": 206264806247097.06
        }
      ],
      "2026-03-28T12:00:00": [
        {
          "star_name": "Vega",
          "altitude_degrees": 80.24127048693711,
          "azimuth_degrees": 262.74488623300357,
          "distance_au": 206264806247097.06
        }
      ],
      "2026-03-28T13:00:00": [
        {
          "star_name": "Vega",
          "altitude_degrees": 68.85869896614254,
          "azimuth_degrees": 273.82525006915114,
          "distance_au": 206264806247097.03
        }
      ],
      "2026-03-28T14:00:00": [],
      "2026-03-28T15:00:00": [],
      "2026-03-28T16:00:00": [],
      "2026-03-28T17:00:00": [],
      "2026-03-28T18:00:00": []
    }
  },
  "europe": {
    "region": "europe",
    "latitude": 48.8566,
    "longitude": 2.3522,
    "star_data_by_hour": {
      "2026-03-27T19:00:00": [],
      "2026-03-27T20:00:00": [],
      "2026-03-27T21:00:00": [],
      "2026-03-27T22:00:00": [],
      "2026-03-27T23:00:00": [],
      "2026-03-28T00:00:00": [],
      "2026-03-28T01:00:00": [],
      "2026-03-28T02:00:00": [],
      "2026-03-28T03:00:00": [],
      "2026-03-28T04:00:00": [
        {
          "star_name": "Vega",
          "altitude_degrees": 65.37098097306438,
          "azimuth_degrees": 102.20158922714148,
          "distance_au": 206264806247097.03
        }
      ],
      "2026-03-28T05:00:00": [
        {
          "star_name": "Vega",
          "altitude_degrees": 74.49286914277705,
          "azimuth_degrees": 124.26810692128142,
          "distance_au": 206264806247097.03
        }
      ],
      "2026-03-28T06:00:00": [
        {
          "star_name": "Vega",
          "altitude_degrees": 79.89126903599727,
          "azimuth_degrees": 173.64431989833224,
          "distance_au": 206264806247097.03
        }
      ],
      "2026-03-28T07:00:00": [
        {
          "star_name": "Vega",
          "altitude_degrees": 75.98497910709811,
          "azimuth_degrees": 229.2339375576264,
          "distance_au": 206264806247096.97
        }
      ],
      "2026-03-28T08:00:00": [
        {
          "star_name": "Vega",
          "altitude_degrees": 67.19667266441381,
          "azimuth_degrees": 254.62680121849095,
          "distance_au": 206264806247097.1
        }
      ],
      "2026-03-28T09:00:00": [],
      "2026-03-28T10:00:00": [],
      "2026-03-28T11:00:00": [],
      "2026-03-28T12:00:00": [],
      "2026-03-28T13:00:00": [],
      "2026-03-28T14:00:00": [],
      "2026-03-28T15:00:00": [],
      "2026-03-28T16:00:00": [],
      "2026-03-28T17:00:00": [],
      "2026-03-28T18:00:00": []
    }
  },
  "asia": {
    "region": "asia",
    "latitude": 35.6895,
    "longitude": 139.6917,
    "star_data_by_hour": {
      "2026-03-27T19:00:00": [
        {
          "star_name": "Vega",
          "altitude_degrees": 66.38296472809864,
          "azimuth_degrees": 73.56220256506532,
          "distance_au": 206264806247096.97
        }
      ],
      "2026-03-27T20:00:00": [
        {
          "star_name": "Vega",
          "altitude_degrees": 78.06029330629792,
          "azimuth_degrees": 70.59253322926672,
          "distance_au": 206264806247097.12
        }
      ],
      "2026-03-27T21:00:00": [
        {
          "star_name": "Vega",
          "altitude_degrees": 86.85977682117732,
          "azimuth_degrees": 352.2754390105774,
          "distance_au": 206264806247097.0
        }
      ],
      "2026-03-27T22:00:00": [
        {
          "star_name": "Vega",
          "altitude_degrees": 77.22915831345628,
          "azimuth_degrees": 288.7277335466132,
          "distance_au": 206264806247097.03
        }
      ],
      "2026-03-27T23:00:00": [
        {
          "star_name": "Vega",
          "altitude_degrees": 65.53971852610871,
          "azimuth_degrees": 286.51046456347717,
          "distance_au": 206264806247097.06
        }
      ],
      "2026-03-28T00:00:00": [],
      "2026-03-28T01:00:00": [],
      "2026-03-28T02:00:00": [],
      "2026-03-28T03:00:00": [],
      "2026-03-28T04:00:00": [],
      "2026-03-28T05:00:00": [],
      "2026-03-28T06:00:00": [],
      "2026-03-28T07:00:00": [],
      "2026-03-28T08:00:00": [
        {
          "star_name": "Betelgeuse",
          "altitude_degrees": 61.51870461493262,
          "azimuth_degrees": 172.2868845618444,
          "distance_au": 206264806247096.5
        }
      ],
      "2026-03-28T09:00:00": [],
      "2026-03-28T10:00:00": [],
      "2026-03-28T11:00:00": [],
      "2026-03-28T12:00:00": [],
      "2026-03-28T13:00:00": [],
      "2026-03-28T14:00:00": [],
      "2026-03-28T15:00:00": [],
      "2026-03-28T16:00:00": [],
      "2026-03-28T17:00:00": [],
      "2026-03-28T18:00:00": []
    }
  },
  "australia": {
    "region": "australia",
    "latitude": -33.8688,
    "longitude": 151.2093,
    "star_data_by_hour": {
      "2026-03-27T19:00:00": [],
      "2026-03-27T20:00:00": [],
      "2026-03-27T21:00:00": [],
      "2026-03-27T22:00:00": [],
      "2026-03-27T23:00:00": [],
      "2026-03-28T00:00:00": [],
      "2026-03-28T01:00:00": [],
      "2026-03-28T02:00:00": [],
      "2026-03-28T03:00:00": [],
      "2026-03-28T04:00:00": [],
      "2026-03-28T05:00:00": [],
      "2026-03-28T06:00:00": [
        {
          "star_name": "Rigel",
          "altitude_degrees": 62.00103037226953,
          "azimuth_degrees": 26.15196302076046,
          "distance_au": 206264806247096.94
        }
      ],
      "2026-03-28T07:00:00": [
        {
          "star_name": "Sirius",
          "altitude_degrees": 65.41377630988319,
          "azimuth_degrees": 50.73844735319358,
          "distance_au": 206264806247096.5
        },
        {
          "star_name": "Rigel",
          "altitude_degrees": 64.15880793678063,
          "azimuth_degrees": 353.23108831836,
          "distance_au": 206264806247096.9
        }
      ],
      "2026-03-28T08:00:00": [
        {
          "star_name": "Sirius",
          "altitude_degrees": 72.3824137333642,
          "azimuth_degrees": 14.755098987819176,
          "distance_au": 206264806247096.53
        }
      ],
      "2026-03-28T09:00:00": [
        {
          "star_name": "Sirius",
          "altitude_degrees": 70.48532914440737,
          "azimuth_degrees": 328.7580223530998,
          "distance_au": 206264806247096.53
        }
      ],
      "2026-03-28T10:00:00": [
        {
          "star_name": "Sirius",
          "altitude_degrees": 61.453907166864376,
          "azimuth_degrees": 300.50453897227624,
          "distance_au": 206264806247096.62
        }
      ],
      "2026-03-28T11:00:00": [],
      "2026-03-28T12:00:00": [],
      "2026-03-28T13:00:00": [],
      "2026-03-28T14:00:00": [],
      "2026-03-28T15:00:00": [],
      "2026-03-28T16:00:00": [],
      "2026-03-28T17:00:00": [],
      "2026-03-28T18:00:00": []
    }
  },
  "africa": {
    "region": "africa",
    "latitude": -1.2921,
    "longitude": 36.8219,
    "star_data_by_hour": {
      "2026-03-27T19:00:00": [],
      "2026-03-27T20:00:00": [],
      "2026-03-27T21:00:00": [],
      "2026-03-27T22:00:00": [],
      "2026-03-27T23:00:00": [],
      "2026-03-28T00:00:00": [],
      "2026-03-28T01:00:00": [],
      "2026-03-28T02:00:00": [],
      "2026-03-28T03:00:00": [],
      "2026-03-28T04:00:00": [],
      "2026-03-28T05:00:00": [],
      "2026-03-28T06:00:00": [],
      "2026-03-28T07:00:00": [],
      "2026-03-28T08:00:00": [],
      "2026-03-28T09:00:00": [],
      "2026-03-28T10:00:00": [],
      "2026-03-28T11:00:00": [],
      "2026-03-28T12:00:00": [],
      "2026-03-28T13:00:00": [
        {
          "star_name": "Rigel",
          "altitude_degrees": 67.82530496495589,
          "azimuth_degrees": 108.7500705272505,
          "distance_au": 206264806247097.0
        }
      ],
      "2026-03-28T14:00:00": [
        {
          "star_name": "Betelgeuse",
          "altitude_degrees": 71.53578098188721,
          "azimuth_degrees": 61.64721446635316,
          "distance_au": 206264806247096.47
        },
        {
          "star_name": "Rigel",
          "altitude_degrees": 80.80397301287206,
          "azimuth_degrees": 138.63596253496632,
          "distance_au": 206264806247096.9
        }
      ],
      "2026-03-28T15:00:00": [
        {
          "star_name": "Sirius",
          "altitude_degrees": 69.47806284974735,
          "azimuth_degrees": 139.62938040570583,
          "distance_au": 206264806247096.5
        },
        {
          "star_name": "Betelgeuse",
          "altitude_degrees": 81.20367433923661,
          "azimuth_degrees": 8.347611380179647,
          "distance_au": 206264806247096.4
        },
        {
          "star_name": "Rigel",
          "altitude_degrees": 78.76543293159105,
          "azimuth_degrees": 231.9480986209787,
          "distance_au": 206264806247096.9
        }
      ],
      "2026-03-28T16:00:00": [
        {
          "star_name": "Sirius",
          "altitude_degrees": 74.49081666382621,
          "azimuth_degrees": 184.74629773932438,
          "distance_au": 206264806247096.62
        },
        {
          "star_name": "Betelgeuse",
          "altitude_degrees": 73.74828844604866,
          "azimuth_degrees": 302.5726051880666,
          "distance_au": 206264806247096.44
        },
        {
          "star_name": "Rigel",
          "altitude_degrees": 65.16771110630836,
          "azimuth_degrees": 253.14920178215516,
          "distance_au": 206264806247096.9
        }
      ],
      "2026-03-28T17:00:00": [
        {
          "star_name": "Sirius",
          "altitude_degrees": 67.67701818037848,
          "azimuth_degrees": 225.2625131538826,
          "distance_au": 206264806247096.56
        }
      ],
      "2026-03-28T18:00:00": []
    }
  },
  "south_america": {
    "region": "south_america",
    "latitude": -23.5505,
    "longitude": -46.6333,
    "star_data_by_hour": {
      "2026-03-27T19:00:00": [
        {
          "star_name": "Rigel",
          "altitude_degrees": 68.71547513336803,
          "azimuth_degrees": 46.24549909049181,
          "distance_au": 206264806247096.9
        }
      ],
      "2026-03-27T20:00:00": [
        {
          "star_name": "Sirius",
          "altitude_degrees": 67.43680132769914,
          "azimuth_degrees": 76.71357641824291,
          "distance_au": 206264806247096.62
        },
        {
          "star_name": "Rigel",
          "altitude_degrees": 74.62007204456991,
          "azimuth_degrees": 1.1916970702722347,
          "distance_au": 206264806247097.06
        }
      ],
      "2026-03-27T21:00:00": [
        {
          "star_name": "Sirius",
          "altitude_degrees": 79.93218931534723,
          "azimuth_degrees": 48.937192405299186,
          "distance_au": 206264806247096.56
        },
        {
          "star_name": "Rigel",
          "altitude_degrees": 69.1336325805319,
          "azimuth_degrees": 315.0726815443873,
          "distance_au": 206264806247096.97
        }
      ],
      "2026-03-27T22:00:00": [
        {
          "star_name": "Sirius",
          "altitude_degrees": 80.45993895540292,
          "azimuth_degrees": 314.1855000899031,
          "distance_au": 206264806247096.56
        }
      ],
      "2026-03-27T23:00:00": [
        {
          "star_name": "Sirius",
          "altitude_degrees": 68.13356033290569,
          "azimuth_degrees": 284.0132169460196,
          "distance_au": 206264806247096.53
        }
      ],
      "2026-03-28T00:00:00": [],
      "2026-03-28T01:00:00": [],
      "2026-03-28T02:00:00": [],
      "2026-03-28T03:00:00": [],
      "2026-03-28T04:00:00": [],
      "2026-03-28T05:00:00": [],
      "2026-03-28T06:00:00": [],
      "2026-03-28T07:00:00": [],
      "2026-03-28T08:00:00": [],
      "2026-03-28T09:00:00": [],
      "2026-03-28T10:00:00": [],
      "2026-03-28T11:00:00": [],
      "2026-03-28T12:00:00": [],
      "2026-03-28T13:00:00": [],
      "2026-03-28T14:00:00": [],
      "2026-03-28T15:00:00": [],
      "2026-03-28T16:00:00": [],
      "2026-03-28T17:00:00": [],
      "2026-03-28T18:00:00": []
    }
  }
}