{
  "north_america": {
    "region": "north_america",
    "latitude": 40.7128,
    "longitude": -74.006,
    "star_data_by_hour": {
      "2025-10-02T10:00:00": [],
      "2025-10-02T11:00:00": [],
      "2025-10-02T12:00:00": [],
      "2025-10-02T13:00:00": [],
      "2025-10-02T14:00:00": [],
      "2025-10-02T15:00:00": [],
      "2025-10-02T16:00:00": [],
      "2025-10-02T17:00:00": [],
      "2025-10-02T18:00:00": [],
      "2025-10-02T19:00:00": [],
      "2025-10-02T20:00:00": [],
      "2025-10-02T21:00:00": [
        {
          "star_name": "Vega",
          "altitude_degrees": 69.52238221512948,
          "azimuth_degrees": 86.60968190131227,
          "distance_au": 206264806247096.84
        }
      ],
      "2025-10-02T22:00:00": [
        {
          "star_name": "Vega",
          "altitude_degrees": 80.90042232856231,
          "azimuth_degrees": 98.31050946532834,
          "distance_au": 206264806247096.9
        }
      ],
      "2025-10-02T23:00:00": [
        {
          "star_name": "Vega",
          "altitude_degrees": 86.73240213369037,
          "azimuth_degrees": 235.4946030896032,
          "distance_au": 206264806247096.9
        }
      ],
      "2025-10-03T00:00:00": [
        {
          "star_name": "Vega",
          "altitude_degrees": 75.68144330573698,
          "azimuth_degrees": 268.38815146698084,
          "distance_au": 206264806247096.9
        }
      ],
      "2025-10-03T01:00:00": [
        {
          "star_name": "Vega",
          "altitude_degrees": 64.305215096195,
          "azimuth_degrees": 276.8088491467442,
          "distance_au": 206264806247096.94
        }
      ],
      "2025-10-03T02:00:00": [],
      "2025-10-03T03:00:00": [],
      "2025-10-03T04:00:00": [],
      "2025-10-03T05:00:00": [],
      "2025-10-03T06:00:00": [],
      "2025-10-03T07:00:00": [],
      "2025-10-03T08:00:00": [],
      "2025-10-03T09:00:00": []
    }
  },
  "europe": {
    "region": "europe",
    "latitude": 48.8566,
    "longitude": 2.3522,
    "star_data_by_hour": {
      "2025-10-02T10:00:00": [],
      "2025-10-02T11:00:00": [],
      "2025-10-02T12:00:00": [],
      "2025-10-02T13:00:00": [],
      "2025-10-02T14:00:00": [],
      "2025-10-02T15:00:00": [],
      "2025-10-02T16:00:00": [
        {
          "star_name": "Vega",
          "altitude_degrees": 69.19952993519539,
          "azimuth_degrees": 109.30697897012567,
          "distance_au": 206264806247096.94
        }
      ],
      "2025-10-02T17:00:00": [
        {
          "star_name": "Vega",
          "altitude_degrees": 77.47178948809518,
          "azimuth_degrees": 139.42302979926353,
          "distance_au": 206264806247096.9
        }
      ],
      "2025-10-02T18:00:00": [
        {
          "star_name": "Vega",
          "altitude_degrees": 79.42229578373012,
          "azimuth_degrees": 199.94265571995123,
          "distance_au": 206264806247096.94
        }
      ],
      "2025-10-02T19:00:00": [
        {
          "star_name": "Vega",
          "altitude_degrees": 72.70913701239836,
          "azimuth_degrees": 241.83657638027447,
          "distance_au": 206264806247096.9
        }
      ],
      "2025-10-02T20:00:00": [
        {
          "star_name": "Vega",
          "altitude_degrees": 63.319662366493745,
          "azimuth_degrees": 261.01265833170163,
          "distance_au": 206264806247096.94
        }
      ],
      "2025-10-02T21:00:00": [],
      "2025-10-02T22:00:00": [],
      "2025-10-02T23:00:00": [],
      "2025-10-03T00:00:00": [],
      "2025-10-03T01:00:00": [],
      "2025-10-03T02:00:00": [],
      "2025-10-03T03:00:00": [],
      "2025-10-03T04:00:00": [],
      "2025-10-03T05:00:00": [],
      "2025-10-03T06:00:00": [],
      "2025-10-03T07:00:00": [],
      "2025-10-03T08:00:00": [],
      "2025-10-03T09:00:00": []
    }
  },
  "asia": {
    "region": "asia",
    "latitude": 35.6895,
    "longitude": 139.6917,
    "star_data_by_hour": {
      "2025-10-02T10:00:00": [
        {
          "star_name": "Vega",
          "altitude_degrees": 72.5529641731301,
          "azimuth_degrees": 286.74992551512986,
          "distance_au": 206264806247096.84
        }
      ],
      "2025-10-02T11:00:00": [
        {
          "star_name": "Vega",
          "altitude_degrees": 60.84719777986587,
          "azimuth_degrees": 287.2371988679271,
          "distance_au": 206264806247096.88
        }
      ],
      "2025-10-02T12:00:00": [],
      "2025-10-02T13:00:00": [],
      "2025-10-02T14:00:00": [],
      "2025-10-02T15:00:00": [],
      "2025-10-02T16:00:00": [],
      "2025-10-02T17:00:00": [],
      "2025-10-02T18:00:00": [],
      "2025-10-02T19:00:00": [],
      "2025-10-02T20:00:00": [
        {
          "star_name": "Betelgeuse",
          "altitude_degrees": 61.64335145669737,
          "azimuth_degrees": 184.8851925853095,
          "distance_au": 206264806247096.1
        }
      ],
      "2025-10-02T21:00:00": [],
      "2025-10-02T22:00:00": [],
      "2025-10-02T23:00:00": [],
      "2025-10-03T00:00:00": [],
      "2025-10-03T01:00:00": [],
      "2025-10-03T02:00:00": [],
      "2025-10-03T03:00:00": [],
      "2025-10-03T04:00:00": [],
      "2025-10-03T05:00:00": [],
      "2025-10-03T06:00:00": [
        {
          "star_name": "Vega",
          "altitude_degrees": 60.15066638281833,
          "azimuth_degrees": 72.6225001812469,
          "distance_au": 206264806247096.9
        }
      ],
      "2025-10-03T07:00:00": [
        {
          "star_name": "Vega",
          "altitude_degrees": 71.85410168517613,
          "azimuth_degrees": 73.3787608912429,
          "distance_au": 206264806247096.94
        }
      ],
      "2025-10-03T08:00:00": [
        {
          "star_name": "Vega",
          "altitude_degrees": 83.28336735259097,
          "azimuth_degrees": 60.10629292022973,
          "distance_au": 206264806247096.9
        }
      ],
      "2025-10-03T09:00:00": [
        {
          "star_name": "Vega",
          "altitude_degrees": 83.221705848728,
          "azimuth_degrees": 299.64671874080585,
          "distance_au": 206264806247096.9
        }
      ]
    }
  },
  "australia": {
    "region": "australia",
    "latitude": -33.8688,
    "longitude": 151.2093,
    "star_data_by_hour": {
      "2025-10-02T10:00:00": [],
      "2025-10-02T11:00:00": [],
      "2025-10-02T12:00:00": [],
      "2025-10-02T13:00:00": [],
      "2025-10-02T14:00:00": [],
      "2025-10-02T15:00:00": [],
      "2025-10-02T16:00:00": [],
      "2025-10-02T17:00:00": [],
      "2025-10-02T18:00:00": [
        {
          "star_name": "Rigel",
          "altitude_degrees": 63.70494710777289,
          "azimuth_degrees": 13.576611499231825,
          "distance_au": 206264806247096.22
        }
      ],
      "2025-10-02T19:00:00": [
        {
          "star_name": "Sirius",
          "altitude_degrees": 68.95196895363418,
          "azimuth_degrees": 38.891027407130636,
          "distance_au": 206264806247096.75
        },
        {
          "star_name": "Rigel",
          "altitude_degrees": 62.99035566063887,
          "azimuth_degrees": 340.0397563388299,
          "distance_au": 206264806247096.28
        }
      ],
      "2025-10-02T20:00:00": [
        {
          "star_name": "Sirius",
          "altitude_degrees": 72.82203809697516,
          "azimuth_degrees": 355.384853926545,
          "distance_au": 206264806247096.72
        }
      ],
      "2025-10-02T21:00:00": [
        {
          "star_name": "Sirius",
          "altitude_degrees": 67.37443213683468,
          "azimuth_degrees": 315.13469581823506,
          "distance_au": 206264806247096.7
        }
      ],
      "2025-10-02T22:00:00": [],
      "2025-10-02T23:00:00": [],
      "2025-10-03T00:00:00": [],
      "2025-10-03T01:00:00": [],
      "2025-10-03T02:00:00": [],
      "2025-10-03T03:00:00": [],
      "2025-10-03T04:00:00": [],
      "2025-10-03T05:00:00": [],
      "2025-10-03T06:00:00": [],
      "2025-10-03T07:00:00": [],
      "2025-10-03T08:00:00": [],
      "2025-10-03T09:00:00": []
    }
  },
  "africa": {
    "region": "africa",
    "latitude": -1.2921,
    "longitude": 36.8219,
    "star_data_by_hour": {
      "2025-10-02T10:00:00": [],
      "2025-10-02T11:00:00": [],
      "2025-10-02T12:00:00": [],
      "2025-10-02T13:00:00": [],
      "2025-10-02T14:00:00": [],
      "2025-10-02T15:00:00": [],
      "2025-10-02T16:00:00": [],
      "2025-10-02T17:00:00": [],
      "2025-10-02T18:00:00": [],
      "2025-10-02T19:00:00": [],
      "2025-10-02T20:00:00": [],
      "2025-10-02T21:00:00": [],
      "2025-10-02T22:00:00": [],
      "2025-10-02T23:00:00": [],
      "2025-10-03T00:00:00": [],
      "2025-10-03T01:00:00": [
        {
          "star_name": "Betelgeuse",
          "altitude_degrees": 63.27665129468289,
          "azimuth_degrees": 70.62077100204904,
          "distance_au": 206264806247096.1
        },
        {
          "star_name": "Rigel",
          "altitude_degrees": 73.43602256255811,
          "azimuth_degrees": 115.00327136820307,
          "distance_au": 206264806247096.3
        }
      ],
      "2025-10-03T02:00:00": [
        {
          "star_name": "Sirius",
          "altitude_degrees": 62.82258891421677,
          "azimuth_degrees": 125.92888950527417,
          "distance_au": 206264806247096.7
        },
        {
          "star_name": "Betelgeuse",
          "altitude_degrees": 76.5432860621355,
          "azimuth_degrees": 49.54210063411789,
          "distance_au": 206264806247096.03
        },
        {
          "star_name": "Rigel",
          "altitude_degrees": 83.12327862660345,
          "azimuth_degrees": 179.2614686067146,
          "distance_au": 206264806247096.28
        }
      ],
      "2025-10-03T03:00:00": [
        {
          "star_name": "Sirius",
          "altitude_degrees": 72.80362828717145,
          "azimuth_degrees": 154.35702283988476,
          "distance_au": 206264806247096.7
        },
        {
          "star_name": "Betelgeuse",
          "altitude_degrees": 80.08550625395479,
          "azimuth_degrees": 331.48093288052985,
          "distance_au": 206264806247096.1
        },
        {
          "star_name": "Rigel",
          "altitude_degrees": 73.59772511379747,
          "azimuth_degrees": 244.7443963013248,
          "distance_au": 206264806247096.22
        }
      ],
      "2025-10-03T04:00:00": [
        {
          "star_name": "Sirius",
          "altitude_degrees": 72.93762363348911,
          "azimuth_degrees": 204.72546485095148,
          "distance_au": 206264806247096.78
        },
        {
          "star_name": "Betelgeuse",
          "altitude_degrees": 68.41762231287423,
          "azimuth_degrees": 294.07299714456616,
          "distance_au": 206264806247096.1
        }
      ],
      "2025-10-03T05:00:00": [
        {
          "star_name": "Sirius",
          "altitude_degrees": 63.076977691390915,
          "azimuth_degrees": 233.71478586840536,
          "distance_au": 206264806247096.7
        }
      ],
      "2025-10-03T06:00:00": [],
      "2025-10-03T07:00:00": [],
      "2025-10-03T08:00:00": [],
      "2025-10-03T09:00:00": []
    }
  },
  "south_america": {
    "region": "south_america",
    "latitude": -23.5505,
    "longitude": -46.6333,
    "star_data_by_hour": {
      "2025-10-02T10:00:00": [
        {
          "star_name": "Sirius",
          "altitude_degrees": 75.89614320667224,
          "azimuth_degrees": 296.45325969727344,
          "distance_au": 206264806247096.7
        }
      ],
      "2025-10-02T11:00:00": [
        {
          "star_name": "Sirius",
          "altitude_degrees": 62.70657395395561,
          "azimuth_degrees": 279.1813617012479,
          "distance_au": 206264806247096.75
        }
      ],
      "2025-10-02T12:00:00": [],
      "2025-10-02T13:00:00": [],
      "2025-10-02T14:00:00": [],
      "2025-10-02T15:00:00": [],
      "2025-10-02T16:00:00": [],
      "2025-10-02T17:00:00": [],
      "2025-10-02T18:00:00": [],
      "2025-10-02T19:00:00": [],
      "2025-10-02T20:00:00": [],
      "2025-10-02T21:00:00": [],
      "2025-10-02T22:00:00": [],
      "2025-10-02T23:00:00": [],
      "2025-10-03T00:00:00": [],
      "2025-10-03T01:00:00": [],
      "2025-10-03T02:00:00": [],
      "2025-10-03T03:00:00": [],
      "2025-10-03T04:00:00": [],
      "2025-10-03T05:00:00": [],
      "2025-10-03T06:00:00": [
        {
          "star_name": "Rigel",
          "altitude_degrees": 62.83200051006767,
          "azimuth_degrees": 59.348313017405225,
          "distance_au": 206264806247096.25
        }
      ],
      "2025-10-03T07:00:00": [
        {
          "star_name": "Sirius",
          "altitude_degrees": 60.20366815886803,
          "azimuth_degrees": 82.59210127592826,
          "distance_au": 206264806247096.7
        },
        {
          "star_name": "Rigel",
          "altitude_degrees": 72.66584631792284,
          "azimuth_degrees": 28.80577928869558,
          "distance_au": 206264806247096.25
        }
      ],
      "2025-10-03T08:00:00": [
        {
          "star_name": "Sirius",
          "altitude_degrees": 73.58443648165013,
          "azimuth_degrees": 68.42374594113136,
          "distance_au": 206264806247096.7
        },
        {
          "star_name": "Rigel",
          "altitude_degrees": 73.33086734477813,
          "azimuth_degrees": 336.25145436047313,
          "distance_au": 206264806247096.22
        }
      ],
      "2025-10-03T09:00:00": [
        {
          "star_name": "Sirius",
          "altitude_degrees": 83.1372934032831,
          "azimuth_degrees": 7.125383610675698,
          "distance_au": 206264806247096.66
        },
        {
          "star_name": "Rigel",
          "altitude_degrees": 64.10820533368594,
          "azimuth_degrees": 302.8890389173732,
          "distance_au": 206264806247096.16
        }
      ]
    }
  }
}