{
  "north_america": {
    "region": "north_america",
    "latitude": 40.7128,
    "longitude": -74.006,
    "star_data_by_hour": {
      "2024-08-11T21:00:00": [],
      "2024-08-11T22:00:00": [],
      "2024-08-11T23:00:00": [],
      "2024-08-12T00:00:00": [
        {
          "star_name": "Vega",
          "altitude_degrees": 65.07496823282824,
          "azimuth_degrees": 83.67705182650704,
          "distance_au": 206264806247096.56
        }
      ],
      "2024-08-12T01:00:00": [
        {
          "star_name": "Vega",
          "altitude_degrees": 76.4558573216368,
          "azimuth_degrees": 92.39933449865858,
          "distance_au": 206264806247096.53
        }
      ],
      "2024-08-12T02:00:00": [
        {
          "star_name": "Vega",
          "altitude_degrees": 87.33000603551781,
          "azimuth_degrees": 134.76027529850344,
          "distance_au": 206264806247096.53
        }
      ],
      "2024-08-12T03:00:00": [
        {
          "star_name": "Vega",
          "altitude_degrees": 80.13116016376412,
          "azimuth_degrees": 262.96154888911065,
          "distance_au": 206264806247096.5
        }
      ],
      "2024-08-12T04:00:00": [
        {
          "star_name": "Vega",
          "altitude_degrees": 68.74782467699919,
          "azimuth_degrees": 273.92091901662326,
          "distance_au": 206264806247096.56
        }
      ],
      "2024-08-12T05:00:00": [],
      "2024-08-12T06:00:00": [],
      "2024-08-12T07:00:00": [],
      "2024-08-12T08:00:00": [],
      "2024-08-12T09:00:00": [],
      "2024-08-12T10:00:00": [],
      "2024-08-12T11:00:00": [],
      "2024-08-12T12:00:00": [],
      "2024-08-12T13:00:00": [],
      "2024-08-12T14:00:00": [],
      "2024-08-12T15:00:00": [],
      "2024-08-12T16:00:00": [],
      "2024-08-12T17:00:00": [],
      "2024-08-12T18:00:00": [],
      "2024-08-12T19:00:00": [],
      "2024-08-12T20:00:00": []
    }
  },
  "europe": {
    "region": "europe",
    "latitude": 48.8566,
    "longitude": 2.3522,
    "star_data_by_hour": {
      "2024-08-11T21:00:00": [
        {
          "star_name": "Vega",
          "altitude_degrees": 79.90830099721687,
          "azimuth_degrees": 174.29916778213962,
          "distance_au": 206264806247096.5
        }
      ],
      "2024-08-11T22:00:00": [
        {
          "star_name": "Vega",
          "altitude_degrees": 75.91585746164391,
          "azimuth_degrees": 229.61820746540795,
          "distance_au": 206264806247096.5
        }
      ],
      "2024-08-11T23:00:00": [
        {
          "star_name": "Vega",
          "altitude_degrees": 67.10620967746854,
          "azimuth_degrees": 254.81425519314274,
          "distance_au": 206264806247096.53
        }
      ],
      "2024-08-12T00:00:00": [],
      "2024-08-12T01:00:00": [],
      "2024-08-12T02:00:00": [],
      "2024-08-12T03:00:00": [],
      "2024-08-12T04:00:00": [],
      "2024-08-12T05:00:00": [],
      "2024-08-12T06:00:00": [],
      "2024-08-12T07:00:00": [],
      "2024-08-12T08:00:00": [],
      "2024-08-12T09:00:00": [],
      "2024-08-12T10:00:00": [],
      "2024-08-12T11:00:00": [],
      "2024-08-12T12:00:00": [],
      "2024-08-12T13:00:00": [],
      "2024-08-12T14:00:00": [],
      "2024-08-12T15:00:00": [],
      "2024-08-12T16:00:00": [],
      "2024-08-12T17:00:00": [],
      "2024-08-12T18:00:00": [],
      "2024-08-12T19:00:00": [
        {
          "star_name": "Vega",
          "altitude_degrees": 66.10268208887197,
          "azimuth_degrees": 103.40918097758237,
          "distance_au": 206264806247096.53
        }
      ],
      "2024-08-12T20:00:00": [
        {
          "star_name": "Vega",
          "altitude_degrees": 75.10566882420481,
          "azimuth_degrees": 126.69906883579829,
          "distance_au": 206264806247096.5
        }
      ]
    }
  },
  "asia": {
    "region": "asia",
    "latitude": 35.6895,
    "longitude": 139.6917,
    "star_data_by_hour": {
      "2024-08-11T21:00:00": [],
      "2024-08-11T22:00:00": [],
      "2024-08-11T23:00:00": [
        {
          "star_name": "Betelgeuse",
          "altitude_degrees": 61.53905760522595,
          "azimuth_degrees": 172.63034666321062,
          "distance_au": 206264806247096.97
        }
      ],
      "2024-08-12T00:00:00": [],
      "2024-08-12T01:00:00": [],
      "2024-08-12T02:00:00": [],
      "2024-08-12T03:00:00": [],
      "2024-08-12T04:00:00": [],
      "2024-08-12T05:00:00": [],
      "2024-08-12T06:00:00": [],
      "2024-08-12T07:00:00": [],
      "2024-08-12T08:00:00": [],
      "2024-08-12T09:00:00": [],
      "2024-08-12T10:00:00": [
        {
          "star_name": "Vega",
          "altitude_degrees": 67.26685636376503,
          "azimuth_degrees": 73.59830030376811,
          "distance_au": 206264806247096.5
        }
      ],
      "2024-08-12T11:00:00": [
        {
          "star_name": "Vega",
          "altitude_degrees": 78.92551865592496,
          "azimuth_degrees": 69.68315444755015,
          "distance_au": 206264806247096.56
        }
      ],
      "2024-08-12T12:00:00": [
        {
          "star_name": "Vega",
          "altitude_degrees": 86.60943937644706,
          "azimuth_degrees": 337.3379114345077,
          "distance_au": 206264806247096.56
        }
      ],
      "2024-08-12T13:00:00": [
        {
          "star_name": "Vega",
          "altitude_degrees": 76.35413845534026,
          "azimuth_degrees": 288.176563355751,
          "distance_au": 206264806247096.53
        }
      ],
      "2024-08-12T14:00:00": [
        {
          "star_name": "Vega",
          "altitude_degrees": 64.65694572643972,
          "azimuth_degrees": 286.62257057578955,
          "distance_au": 206264806247096.56
        }
      ],
      "2024-08-12T15:00:00": [],
      "2024-08-12T16:00:00": [],
      "2024-08-12T17:00:00": [],
      "2024-08-12T18:00:00": [],
      "2024-08-12T19:00:00": [],
      "2024-08-12T20:00:00": []
    }
  },
  "australia": {
    "region": "australia",
    "latitude": -33.8688,
    "longitude": 151.2093,
    "star_data_by_hour": {
      "2024-08-11T21:00:00": [
        {
          "star_name": "Rigel",
          "altitude_degrees": 62.05680274431152,
          "azimuth_degrees": 25.831359566221952,
          "distance_au": 206264806247097.0
        }
      ],
      "2024-08-11T22:00:00": [
        {
          "star_name": "Sirius",
          "altitude_degrees": 65.51301534505363,
          "azimuth_degrees": 50.44395643746223,
          "distance_au": 206264806247097.44
        },
        {
          "star_name": "Rigel",
          "altitude_degrees": 64.13913675311052,
          "azimuth_degrees": 352.8660628902522,
          "distance_au": 206264806247097.0
        }
      ],
      "2024-08-11T23:00:00": [
        {
          "star_name": "Sirius",
          "altitude_degrees": 72.40849774577026,
          "azimuth_degrees": 14.241576037330674,
          "distance_au": 206264806247097.44
        }
      ],
      "2024-08-12T00:00:00": [
        {
          "star_name": "Sirius",
          "altitude_degrees": 70.40683053071638,
          "azimuth_degrees": 328.35012015091934,
          "distance_au": 206264806247097.44
        }
      ],
      "2024-08-12T01:00:00": [
        {
          "star_name": "Sirius",
          "altitude_degrees": 61.33082281205624,
          "azimuth_degrees": 300.29939042972575,
          "distance_au": 206264806247097.4
        }
      ],
      "2024-08-12T02:00:00": [],
      "2024-08-12T03:00:00": [],
      "2024-08-12T04:00:00": [],
      "2024-08-12T05:00:00": [],
      "2024-08-12T06:00:00": [],
      "2024-08-12T07:00:00": [],
      "2024-08-12T08:00:00": [],
      "2024-08-12T09:00:00": [],
      "2024-08-12T10:00:00": [],
      "2024-08-12T11:00:00": [],
      "2024-08-12T12:00:00": [],
      "2024-08-12T13:00:00": [],
      "2024-08-12T14:00:00": [],
      "2024-08-12T15:00:00": [],
      "2024-08-12T16:00:00": [],
      "2024-08-12T17:00:00": [],
      "2024-08-12T18:00:00": [],
      "2024-08-12T19:00:00": [],
      "2024-08-12T20:00:00": []
    }
  },
  "africa": {
    "region": "africa",
    "latitude": -1.2921,
    "longitude": 36.8219,
    "star_data_by_hour": {
      "2024-08-11T21:00:00": [],
      "2024-08-11T22:00:00": [],
      "2024-08-11T23:00:00": [],
      "2024-08-12T00:00:00": [],
      "2024-08-12T01:00:00": [],
      "2024-08-12T02:00:00": [],
      "2024-08-12T03:00:00": [],
      "2024-08-12T04:00:00": [
        {
          "star_name": "Rigel",
          "altitude_degrees": 67.97955798130121,
          "azimuth_degrees": 108.86630979693581,
          "distance_au": 206264806247097.06
        }
      ],
      "2024-08-12T05:00:00": [
        {
          "star_name": "Betelgeuse",
          "altitude_degrees": 71.68072079548303,
          "azimuth_degrees": 61.397617016888915,
          "distance_au": 206264806247097.03
        },
        {
          "star_name": "Rigel",
          "altitude_degrees": 80.91272573557224,
          "azimuth_degrees": 139.3774353561423,
          "distance_au": 206264806247097.1
        }
      ],
      "2024-08-12T06:00:00": [
        {
          "star_name": "Sirius",
          "altitude_degrees": 69.59013860485733,
          "azimuth_degrees": 139.94563118314724,
          "distance_au": 206264806247097.44
        },
        {
          "star_name": "Betelgeuse",
          "altitude_degrees": 81.2236665787263,
          "azimuth_degrees": 7.275719384652092,
          "distance_au": 206264806247097.0
        },
        {
          "star_name": "Rigel",
          "altitude_degrees": 78.63957078338926,
          "azimuth_degrees": 232.45498543094467,
          "distance_au": 206264806247097.06
        }
      ],
      "2024-08-12T07:00:00": [
        {
          "star_name": "Sirius",
          "altitude_degrees": 74.48461949054031,
          "azimuth_degrees": 185.33451156854437,
          "distance_au": 206264806247097.38
        },
        {
          "star_name": "Betelgeuse",
          "altitude_degrees": 73.60655875445285,
          "azimuth_degrees": 302.27242119769426,
          "distance_au": 206264806247097.0
        },
        {
          "star_name": "Rigel",
          "altitude_degrees": 65.01361212611508,
          "azimuth_degrees": 253.25412273951517,
          "distance_au": 206264806247097.03
        }
      ],
      "2024-08-12T08:00:00": [
        {
          "star_name": "Sirius",
          "altitude_degrees": 67.565658709978,
          "azimuth_degrees": 225.5547978748986,
          "distance_au": 206264806247097.38
        }
      ],
      "2024-08-12T09:00:00": [],
      "2024-08-12T10:00:00": [],
      "2024-08-12T11:00:00": [],
      "2024-08-12T12:00:00": [],
      "2024-08-12T13:00:00": [],
      "2024-08-12T14:00:00": [],
      "2024-08-12T15:00:00": [],
      "2024-08-12T16:00:00": [],
      "2024-08-12T17:00:00": [],
      "2024-08-12T18:00:00": [],
      "2024-08-12T19:00:00": [],
      "2024-08-12T20:00:00": []
    }
  },
  "south_america": {
    "region": "south_america",
    "latitude": -23.5505,
    "longitude": -46.6333,
    "star_data_by_hour": {
      "2024-08-11T21:00:00": [],
      "2024-08-11T22:00:00": [],
      "2024-08-11T23:00:00": [],
      "2024-08-12T00:00:00": [],
      "2024-08-12T01:00:00": [],
      "2024-08-12T02:00:00": [],
      "2024-08-12T03:00:00": [],
      "2024-08-12T04:00:00": [],
      "2024-08-12T05:00:00": [],
      "2024-08-12T06:00:00": [],
      "2024-08-12T07:00:00": [],
      "2024-08-12T08:00:00": [],
      "2024-08-12T09:00:00": [],
      "2024-08-12T10:00:00": [
        {
          "star_name": "Rigel",
          "altitude_degrees": 69.45740727074265,
          "azimuth_degrees": 43.83520646420036,
          "distance_au": 206264806247097.1
        }
      ],
      "2024-08-12T11:00:00": [
        {
          "star_name": "Sirius",
          "altitude_degrees": 68.45726610242268,
          "azimuth_degrees": 75.61128938868546,
          "distance_au": 206264806247097.4
        },
        {
          "star_name": "Rigel",
          "altitude_degrees": 74.59920938943927,
          "azimuth_degrees": 356.9112610212565,
          "distance_au": 206264806247097.1
        }
      ],
      "2024-08-12T12:00:00": [
        {
          "star_name": "Sirius",
          "altitude_degrees": 80.69223863287235,
          "azimuth_degrees": 44.197410378071105,
          "distance_au": 206264806247097.47
        },
        {
          "star_name": "Rigel",
          "altitude_degrees": 68.37304696144656,
          "azimuth_degrees": 312.74392380359876,
          "distance_au": 206264806247097.03
        }
      ],
      "2024-08-12T13:00:00": [
        {
          "star_name": "Sirius",
          "altitude_degrees": 79.6698175149012,
          "azimuth_degrees": 309.73564570969006,
          "distance_au": 206264806247097.44
        }
      ],
      "2024-08-12T14:00:00": [
        {
          "star_name": "Sirius",
          "altitude_degrees": 67.10554936845429,
          "azimuth_degrees": 282.9766238805574,
          "distance_au": 206264806247097.44
        }
      ],
      "2024-08-12T15:00:00": [],
      "2024-08-12T16:00:00": [],
      "2024-08-12T17:00:00": [],
      "2024-08-12T18:00:00": [],
      "2024-08-12T19:00:00": [],
      "2024-08-12T20:00:00": []
    }
  }
}