{
  "north_america": {
    "region": "north_america",
    "latitude": 40.7128,
    "longitude": -74.006,
    "star_data_by_hour": {
      "2026-05-08T11:00:00": [
        {
          "star_name": "Vega",
          "altitude_degrees": 61.084233246127845,
          "azimuth_degrees": 278.73750828146666,
          "distance_au": 206264806247096.62
        }
      ],
      "2026-05-08T12:00:00": [],
      "2026-05-08T13:00:00": [],
      "2026-05-08T14:00:00": [],
      "2026-05-08T15:00:00": [],
      "2026-05-08T16:00:00": [],
      "2026-05-08T17:00:00": [],
      "2026-05-08T18:00:00": [],
      "2026-05-08T19:00:00": [],
      "2026-05-08T20:00:00": [],
      "2026-05-08T21:00:00": [],
      "2026-05-08T22:00:00": [],
      "2026-05-08T23:00:00": [],
      "2026-05-09T00:00:00": [],
      "2026-05-09T01:00:00": [],
      "2026-05-09T02:00:00": [],
      "2026-05-09T03:00:00": [],
      "2026-05-09T04:00:00": [],
      "2026-05-09T05:00:00": [],
      "2026-05-09T06:00:00": [
        {
          "star_name": "Vega",
          "altitude_degrees": 62.15553240615867,
          "azimuth_degrees": 81.90099379680461,
          "distance_au": 206264806247096.66
        }
      ],
      "2026-05-09T07:00:00": [
        {
          "star_name": "Vega",
          "altitude_degrees": 73.51385811419559,
          "azimuth_degrees": 89.6873991069085,
          "distance_au": 206264806247096.7
        }
      ],
      "2026-05-09T08:00:00": [
        {
          "star_name": "Vega",
          "altitude_degrees": 84.78534209045996,
          "azimuth_degrees": 109.45228111054931,
          "distance_au": 206264806247096.78
        }
      ],
      "2026-05-09T09:00:00": [
        {
          "star_name": "Vega",
          "altitude_degrees": 83.02710225831778,
          "azimuth_degrees": 256.92488717929143,
          "distance_au": 206264806247096.75
        }
      ],
      "2026-05-09T10:00:00": [
        {
          "star_name": "Vega",
          "altitude_degrees": 71.6842455364262,
          "azimuth_degrees": 271.78092907325805,
          "distance_au": 206264806247096.62
        }
      ]
    }
  },
  "europe": {
    "region": "europe",
    "latitude": 48.8566,
    "longitude": 2.3522,
    "star_data_by_hour": {
      "2026-05-08T11:00:00": [],
      "2026-05-08T12:00:00": [],
      "2026-05-08T13:00:00": [],
      "2026-05-08T14:00:00": [],
      "2026-05-08T15:00:00": [],
      "2026-05-08T16:00:00": [],
      "2026-05-08T17:00:00": [],
      "2026-05-08T18:00:00": [],
      "2026-05-08T19:00:00": [],
      "2026-05-08T20:00:00": [],
      "2026-05-08T21:00:00": [],
      "2026-05-08T22:00:00": [],
      "2026-05-08T23:00:00": [],
      "2026-05-09T00:00:00": [],
      "2026-05-09T01:00:00": [
        {
          "star_name": "Vega",
          "altitude_degrees": 62.95647980702517,
          "azimuth_degrees": 98.4775730286749,
          "distance_au": 206264806247096.66
        }
      ],
      "2026-05-09T02:00:00": [
        {
          "star_name": "Vega",
          "altitude_degrees": 72.3824436671832,
          "azimuth_degrees": 117.23080316607661,
          "distance_au": 206264806247096.66
        }
      ],
      "2026-05-09T03:00:00": [
        {
          "star_name": "Vega",
          "altitude_degrees": 79.28441184246464,
          "azimuth_degrees": 157.85207120154803,
          "distance_au": 206264806247096.62
        }
      ],
      "2026-05-09T04:00:00": [
        {
          "star_name": "Vega",
          "altitude_degrees": 77.69725054943153,
          "azimuth_degrees": 218.87324923903054,
          "distance_au": 206264806247096.78
        }
      ],
      "2026-05-09T05:00:00": [
        {
          "star_name": "Vega",
          "altitude_degrees": 69.53664271323437,
          "azimuth_degrees": 249.93498073536927,
          "distance_au": 206264806247096.66
        }
      ],
      "2026-05-09T06:00:00": [],
      "2026-05-09T07:00:00": [],
      "2026-05-09T08:00:00": [],
      "2026-05-09T09:00:00": [],
      "2026-05-09T10:00:00": []
    }
  },
  "asia": {
    "region": "asia",
    "latitude": 35.6895,
    "longitude": 139.6917,
    "star_data_by_hour": {
      "2026-05-08T11:00:00": [],
      "2026-05-08T12:00:00": [],
      "2026-05-08T13:00:00": [],
      "2026-05-08T14:00:00": [],
      "2026-05-08T15:00:00": [],
      "2026-05-08T16:00:00": [
        {
          "star_name": "Vega",
          "altitude_degrees": 63.47810460413585,
          "azimuth_degrees": 73.23268475435407,
          "distance_au": 206264806247096.72
        }
      ],
      "2026-05-08T17:00:00": [
        {
          "star_name": "Vega",
          "altitude_degrees": 75.18362994133435,
          "azimuth_degrees": 72.4492857517709,
          "distance_au": 206264806247096.62
        }
      ],
      "2026-05-08T18:00:00": [
        {
          "star_name": "Vega",
          "altitude_degrees": 85.98364440537621,
          "azimuth_degrees": 38.26373580888968,
          "distance_au": 206264806247096.62
        }
      ],
      "2026-05-08T19:00:00": [
        {
          "star_name": "Vega",
          "altitude_degrees": 80.07525136479687,
          "azimuth_degrees": 291.7902241297063,
          "distance_au": 206264806247096.62
        }
      ],
      "2026-05-08T20:00:00": [
        {
          "star_name": "Vega",
          "altitude_degrees": 68.44730148623819,
          "azimuth_degrees": 286.3566983215799,
          "distance_au": 206264806247096.7
        }
      ],
      "2026-05-08T21:00:00": [],
      "2026-05-08T22:00:00": [],
      "2026-05-08T23:00:00": [],
      "2026-05-09T00:00:00": [],
      "2026-05-09T01:00:00": [],
      "2026-05-09T02:00:00": [],
      "2026-05-09T03:00:00": [],
      "2026-05-09T04:00:00": [],
      "2026-05-09T05:00:00": [
        {
          "star_name": "Betelgeuse",
          "altitude_degrees": 60.91528074193049,
          "azimuth_degrees": 164.7154865276342,
          "distance_au": 206264806247097.22
        }
      ],
      "2026-05-09T06:00:00": [
        {
          "star_name": "Betelgeuse",
          "altitude_degrees": 60.873720261972885,
          "azimuth_degrees": 195.66606842657237,
          "distance_au": 206264806247097.22
        }
      ],
      "2026-05-09T07:00:00": [],
      "2026-05-09T08:00:00": [],
      "2026-05-09T09:00:00": [],
      "2026-05-09T10:00:00": []
    }
  },
  "australia": {
    "region": "australia",
    "latitude": -33.8688,
    "longitude": 151.2093,
    "star_data_by_hour": {
      "2026-05-08T11:00:00": [],
      "2026-05-08T12:00:00": [],
      "2026-05-08T13:00:00": [],
      "2026-05-08T14:00:00": [],
      "2026-05-08T15:00:00": [],
      "2026-05-08T16:00:00": [],
      "2026-05-08T17:00:00": [],
      "2026-05-08T18:00:00": [],
      "2026-05-08T19:00:00": [],
      "2026-05-08T20:00:00": [],
      "2026-05-08T21:00:00": [],
      "2026-05-08T22:00:00": [],
      "2026-05-08T23:00:00": [],
      "2026-05-09T00:00:00": [],
      "2026-05-09T01:00:00": [],
      "2026-05-09T02:00:00": [],
      "2026-05-09T03:00:00": [
        {
          "star_name": "Rigel",
          "altitude_degrees": 60.469279724831395,
          "azimuth_degrees": 33.1256770534961,
          "distance_au": 206264806247097.6
        }
      ],
      "2026-05-09T04:00:00": [
        {
          "star_name": "Sirius",
          "altitude_degrees": 62.92124530544219,
          "azimuth_degrees": 56.59782118554066,
          "distance_au": 206264806247097.16
        },
        {
          "star_name": "Rigel",
          "altitude_degrees": 64.29454142174609,
          "azimuth_degrees": 1.7099534433271681,
          "distance_au": 206264806247097.66
        }
      ],
      "2026-05-09T05:00:00": [
        {
          "star_name": "Sirius",
          "altitude_degrees": 71.30976504034345,
          "azimuth_degrees": 25.688108943433228,
          "distance_au": 206264806247097.06
        },
        {
          "star_name": "Rigel",
          "altitude_degrees": 61.12428841198011,
          "azimuth_degrees": 329.6020578438582,
          "distance_au": 206264806247097.56
        }
      ],
      "2026-05-09T06:00:00": [
        {
          "star_name": "Sirius",
          "altitude_degrees": 71.84994308198725,
          "azimuth_degrees": 338.98110729710345,
          "distance_au": 206264806247097.12
        }
      ],
      "2026-05-09T07:00:00": [
        {
          "star_name": "Sirius",
          "altitude_degrees": 64.04192761021136,
          "azimuth_degrees": 305.8676248580009,
          "distance_au": 206264806247097.1
        }
      ],
      "2026-05-09T08:00:00": [],
      "2026-05-09T09:00:00": [],
      "2026-05-09T10:00:00": []
    }
  },
  "africa": {
    "region": "africa",
    "latitude": -1.2921,
    "longitude": 36.8219,
    "star_data_by_hour": {
      "2026-05-08T11:00:00": [
        {
          "star_name": "Betelgeuse",
          "altitude_degrees": 67.28377499699207,
          "azimuth_degrees": 67.17150067776004,
          "distance_au": 206264806247097.2
        },
        {
          "star_name": "Rigel",
          "altitude_degrees": 77.20193936400847,
          "azimuth_degrees": 122.86189853399634,
          "distance_au": 206264806247097.53
        }
      ],
      "2026-05-08T12:00:00": [
        {
          "star_name": "Sirius",
          "altitude_degrees": 66.17224048843744,
          "azimuth_degrees": 131.47639812995956,
          "distance_au": 206264806247097.12
        },
        {
          "star_name": "Betelgeuse",
          "altitude_degrees": 79.44147747759122,
          "azimuth_degrees": 34.40159553166535,
          "distance_au": 206264806247097.22
        },
        {
          "star_name": "Rigel",
          "altitude_degrees": 81.94439585177831,
          "azimuth_degrees": 211.20440656320068,
          "distance_au": 206264806247097.6
        }
      ],
      "2026-05-08T13:00:00": [
        {
          "star_name": "Sirius",
          "altitude_degrees": 74.19110476587642,
          "azimuth_degrees": 168.02081318515064,
          "distance_au": 206264806247097.16
        },
        {
          "star_name": "Betelgeuse",
          "altitude_degrees": 77.46107920833936,
          "azimuth_degrees": 314.0816683325277,
          "distance_au": 206264806247097.16
        },
        {
          "star_name": "Rigel",
          "altitude_degrees": 69.63324381357151,
          "azimuth_degrees": 249.64658878875022,
          "distance_au": 206264806247097.53
        }
      ],
      "2026-05-08T14:00:00": [
        {
          "star_name": "Sirius",
          "altitude_degrees": 70.75267150169563,
          "azimuth_degrees": 215.9364025693497,
          "distance_au": 206264806247097.12
        },
        {
          "star_name": "Betelgeuse",
          "altitude_degrees": 64.44137455950634,
          "azimuth_degrees": 290.25548855735906,
          "distance_au": 206264806247097.28
        }
      ],
      "2026-05-08T15:00:00": [],
      "2026-05-08T16:00:00": [],
      "2026-05-08T17:00:00": [],
      "2026-05-08T18:00:00": [],
      "2026-05-08T19:00:00": [],
      "2026-05-08T20:00:00": [],
      "2026-05-08T21:00:00": [],
      "2026-05-08T22:00:00": [],
      "2026-05-08T23:00:00": [],
      "2026-05-09T00:00:00": [],
      "2026-05-09T01:00:00": [],
      "2026-05-09T02:00:00": [],
      "2026-05-09T03:00:00": [],
      "2026-05-09T04:00:00": [],
      "2026-05-09T05:00:00": [],
      "2026-05-09T06:00:00": [],
      "2026-05-09T07:00:00": [],
      "2026-05-09T08:00:00": [],
      "2026-05-09T09:00:00": [],
      "2026-05-09T10:00:00": [
        {
          "star_name": "Rigel",
          "altitude_degrees": 64.27409971186229,
          "azimuth_degrees": 106.30609406981716,
          "distance_au": 206264806247097.62
        }
      ]
    }
  },
  "south_america": {
    "region": "south_america",
    "latitude": -23.5505,
    "longitude": -46.6333,
    "star_data_by_hour": {
      "2026-05-08T11:00:00": [],
      "2026-05-08T12:00:00": [],
      "2026-05-08T13:00:00": [],
      "2026-05-08T14:00:00": [],
      "2026-05-08T15:00:00": [],
      "2026-05-08T16:00:00": [
        {
          "star_name": "Rigel",
          "altitude_degrees": 66.10994670722508,
          "azimuth_degrees": 53.049460936979855,
          "distance_au": 206264806247097.56
        }
      ],
      "2026-05-08T17:00:00": [
        {
          "star_name": "Sirius",
          "altitude_degrees": 64.09478510857952,
          "azimuth_degrees": 79.74739066254165,
          "distance_au": 206264806247097.06
        },
        {
          "star_name": "Rigel",
          "altitude_degrees": 74.14143935725903,
          "azimuth_degrees": 14.798907520268932,
          "distance_au": 206264806247097.5
        }
      ],
      "2026-05-08T18:00:00": [
        {
          "star_name": "Sirius",
          "altitude_degrees": 77.14032842718272,
          "azimuth_degrees": 60.19537885306464,
          "distance_au": 206264806247097.1
        },
        {
          "star_name": "Rigel",
          "altitude_degrees": 71.35795276775524,
          "azimuth_degrees": 323.791378985927,
          "distance_au": 206264806247097.56
        }
      ],
      "2026-05-08T19:00:00": [
        {
          "star_name": "Sirius",
          "altitude_degrees": 82.48257374748174,
          "azimuth_degrees": 334.22353591232616,
          "distance_au": 206264806247097.12
        },
        {
          "star_name": "Rigel",
          "altitude_degrees": 60.70311674651,
          "azimuth_degrees": 297.37993668992954,
          "distance_au": 206264806247097.56
        }
      ],
      "2026-05-08T20:00:00": [
        {
          "star_name": "Sirius",
          "altitude_degrees": 71.41454399816573,
          "azimuth_degrees": 288.0635621607543,
          "distance_au": 206264806247097.1
        }
      ],
      "2026-05-08T21:00:00": [],
      "2026-05-08T22:00:00": [],
      "2026-05-08T23:00:00": [],
      "2026-05-09T00:00:00": [],
      "2026-05-09T01:00:00": [],
      "2026-05-09T02:00:00": [],
      "2026-05-09T03:00:00": [],
      "2026-05-09T04:00:00": [],
      "2026-05-09T05:00:00": [],
      "2026-05-09T06:00:00": [],
      "2026-05-09T07:00:00": [],
      "2026-05-09T08:00:00": [],
      "2026-05-09T09:00:00": [],
      "2026-05-09T10:00:00": []
    }
  }
}