{
  "north_america": {
    "region": "north_america",
    "latitude": 40.7128,
    "longitude": -74.006,
    "star_data_by_hour": {
      "2025-01-14T02:00:00": [],
      "2025-01-14T03:00:00": [],
      "2025-01-14T04:00:00": [],
      "2025-01-14T05:00:00": [],
      "2025-01-14T06:00:00": [],
      "2025-01-14T07:00:00": [],
      "2025-01-14T08:00:00": [],
      "2025-01-14T09:00:00": [],
      "2025-01-14T10:00:00": [],
      "2025-01-14T11:00:00": [],
      "2025-01-14T12:00:00": [],
      "2025-01-14T13:00:00": [],
      "2025-01-14T14:00:00": [
        {
          "star_name": "Vega",
          "altitude_degrees": 67.60844666896658,
          "azimuth_degrees": 85.32217271208134,
          "distance_au": 206264806247097.5
        }
      ],
      "2025-01-14T15:00:00": [
        {
          "star_name": "Vega",
          "altitude_degrees": 78.99521693328278,
          "azimuth_degrees": 95.4081096452623,
          "distance_au": 206264806247097.47
        }
      ],
      "2025-01-14T16:00:00": [
        {
          "star_name": "Vega",
          "altitude_degrees": 87.96110510248553,
          "azimuth_degrees": 200.74904921896803,
          "distance_au": 206264806247097.44
        }
      ],
      "2025-01-14T17:00:00": [
        {
          "star_name": "Vega",
          "altitude_degrees": 77.59472781696265,
          "azimuth_degrees": 266.33720344989683,
          "distance_au": 206264806247097.5
        }
      ],
      "2025-01-14T18:00:00": [
        {
          "star_name": "Vega",
          "altitude_degrees": 66.209197030068,
          "azimuth_degrees": 275.59198374906947,
          "distance_au": 206264806247097.5
        }
      ],
      "2025-01-14T19:00:00": [],
      "2025-01-14T20:00:00": [],
      "2025-01-14T21:00:00": [],
      "2025-01-14T22:00:00": [],
      "2025-01-14T23:00:00": [],
      "2025-01-15T00:00:00": [],
      "2025-01-15T01:00:00": []
    }
  },
  "europe": {
    "region": "europe",
    "latitude": 48.8566,
    "longitude": 2.3522,
    "star_data_by_hour": {
      "2025-01-14T02:00:00": [],
      "2025-01-14T03:00:00": [],
      "2025-01-14T04:00:00": [],
      "2025-01-14T05:00:00": [],
      "2025-01-14T06:00:00": [],
      "2025-01-14T07:00:00": [],
      "2025-01-14T08:00:00": [],
      "2025-01-14T09:00:00": [
        {
          "star_name": "Vega",
          "altitude_degrees": 67.6102832598481,
          "azimuth_degrees": 106.13795866066849,
          "distance_au": 206264806247097.47
        }
      ],
      "2025-01-14T10:00:00": [
        {
          "star_name": "Vega",
          "altitude_degrees": 76.3072060702184,
          "azimuth_degrees": 132.40286164566317,
          "distance_au": 206264806247097.47
        }
      ],
      "2025-01-14T11:00:00": [
        {
          "star_name": "Vega",
          "altitude_degrees": 79.83557053931132,
          "azimuth_degrees": 189.22132088082247,
          "distance_au": 206264806247097.44
        }
      ],
      "2025-01-14T12:00:00": [
        {
          "star_name": "Vega",
          "altitude_degrees": 74.13777910593407,
          "azimuth_degrees": 237.0724884004745,
          "distance_au": 206264806247097.47
        }
      ],
      "2025-01-14T13:00:00": [
        {
          "star_name": "Vega",
          "altitude_degrees": 64.9531273975867,
          "azimuth_degrees": 258.4835943796777,
          "distance_au": 206264806247097.5
        }
      ],
      "2025-01-14T14:00:00": [],
      "2025-01-14T15:00:00": [],
      "2025-01-14T16:00:00": [],
      "2025-01-14T17:00:00": [],
      "2025-01-14T18:00:00": [],
      "2025-01-14T19:00:00": [],
      "2025-01-14T20:00:00": [],
      "2025-01-14T21:00:00": [],
      "2025-01-14T22:00:00": [],
      "2025-01-14T23:00:00": [],
      "2025-01-15T00:00:00": [],
      "2025-01-15T01:00:00": []
    }
  },
  "asia": {
    "region": "asia",
    "latitude": 35.6895,
    "longitude": 139.6917,
    "star_data_by_hour": {
      "2025-01-14T02:00:00": [
        {
          "star_name": "Vega",
          "altitude_degrees": 85.51968165197525,
          "azimuth_degrees": 315.2105781578495,
          "distance_au": 206264806247097.5
        }
      ],
      "2025-01-14T03:00:00": [
        {
          "star_name": "Vega",
          "altitude_degrees": 74.51792479127398,
          "azimuth_degrees": 287.2838917422768,
          "distance_au": 206264806247097.44
        }
      ],
      "2025-01-14T04:00:00": [
        {
          "star_name": "Vega",
          "altitude_degrees": 62.81040433654018,
          "azimuth_degrees": 286.8717445900229,
          "distance_au": 206264806247097.53
        }
      ],
      "2025-01-14T05:00:00": [],
      "2025-01-14T06:00:00": [],
      "2025-01-14T07:00:00": [],
      "2025-01-14T08:00:00": [],
      "2025-01-14T09:00:00": [],
      "2025-01-14T10:00:00": [],
      "2025-01-14T11:00:00": [],
      "2025-01-14T12:00:00": [],
      "2025-01-14T13:00:00": [
        {
          "star_name": "Betelgeuse",
          "altitude_degrees": 61.72126461752982,
          "azimuth_degrees": 179.58451345915861,
          "distance_au": 206264806247095.38
        }
      ],
      "2025-01-14T14:00:00": [],
      "2025-01-14T15:00:00": [],
      "2025-01-14T16:00:00": [],
      "2025-01-14T17:00:00": [],
      "2025-01-14T18:00:00": [],
      "2025-01-14T19:00:00": [],
      "2025-01-14T20:00:00": [],
      "2025-01-14T21:00:00": [],
      "2025-01-14T22:00:00": [],
      "2025-01-14T23:00:00": [],
      "2025-01-15T00:00:00": [
        {
          "star_name": "Vega",
          "altitude_degrees": 69.88466558834507,
          "azimuth_degrees": 73.6075253674273,
          "distance_au": 206264806247097.44
        }
      ],
      "2025-01-15T01:00:00": [
        {
          "star_name": "Vega",
          "altitude_degrees": 81.45409581718765,
          "azimuth_degrees": 65.67202181169928,
          "distance_au": 206264806247097.47
        }
      ]
    }
  },
  "australia": {
    "region": "australia",
    "latitude": -33.8688,
    "longitude": 151.2093,
    "star_data_by_hour": {
      "2025-01-14T02:00:00": [],
      "2025-01-14T03:00:00": [],
      "2025-01-14T04:00:00": [],
      "2025-01-14T05:00:00": [],
      "2025-01-14T06:00:00": [],
      "2025-01-14T07:00:00": [],
      "2025-01-14T08:00:00": [],
      "2025-01-14T09:00:00": [],
      "2025-01-14T10:00:00": [],
      "2025-01-14T11:00:00": [
        {
          "star_name": "Rigel",
          "altitude_degrees": 63.118551421328135,
          "azimuth_degrees": 19.031761098546852,
          "distance_au": 206264806247095.9
        }
      ],
      "2025-01-14T12:00:00": [
        {
          "star_name": "Sirius",
          "altitude_degrees": 67.55504623137946,
          "azimuth_degrees": 44.26864956532538,
          "distance_au": 206264806247095.84
        },
        {
          "star_name": "Rigel",
          "altitude_degrees": 63.620479057059875,
          "azimuth_degrees": 345.45044369216834,
          "distance_au": 206264806247095.9
        }
      ],
      "2025-01-14T13:00:00": [
        {
          "star_name": "Sirius",
          "altitude_degrees": 72.84440504235658,
          "azimuth_degrees": 3.6307922457805684,
          "distance_au": 206264806247095.88
        }
      ],
      "2025-01-14T14:00:00": [
        {
          "star_name": "Sirius",
          "altitude_degrees": 68.79571511522045,
          "azimuth_degrees": 320.4265230568336,
          "distance_au": 206264806247095.88
        }
      ],
      "2025-01-14T15:00:00": [],
      "2025-01-14T16:00:00": [],
      "2025-01-14T17:00:00": [],
      "2025-01-14T18:00:00": [],
      "2025-01-14T19:00:00": [],
      "2025-01-14T20:00:00": [],
      "2025-01-14T21:00:00": [],
      "2025-01-14T22:00:00": [],
      "2025-01-14T23:00:00": [],
      "2025-01-15T00:00:00": [],
      "2025-01-15T01:00:00": []
    }
  },
  "africa": {
    "region": "africa",
    "latitude": -1.2921,
    "longitude": 36.8219,
    "star_data_by_hour": {
      "2025-01-14T02:00:00": [],
      "2025-01-14T03:00:00": [],
      "2025-01-14T04:00:00": [],
      "2025-01-14T05:00:00": [],
      "2025-01-14T06:00:00": [],
      "2025-01-14T07:00:00": [],
      "2025-01-14T08:00:00": [],
      "2025-01-14T09:00:00": [],
      "2025-01-14T10:00:00": [],
      "2025-01-14T11:00:00": [],
      "2025-01-14T12:00:00": [],
      "2025-01-14T13:00:00": [],
      "2025-01-14T14:00:00": [],
      "2025-01-14T15:00:00": [],
      "2025-01-14T16:00:00": [],
      "2025-01-14T17:00:00": [],
      "2025-01-14T18:00:00": [
        {
          "star_name": "Betelgeuse",
          "altitude_degrees": 60.87389098974979,
          "azimuth_degrees": 72.20794977432399,
          "distance_au": 206264806247095.5
        },
        {
          "star_name": "Rigel",
          "altitude_degrees": 71.10745516745531,
          "azimuth_degrees": 111.91839865868924,
          "distance_au": 206264806247096.0
        }
      ],
      "2025-01-14T19:00:00": [
        {
          "star_name": "Sirius",
          "altitude_degrees": 60.730261529466965,
          "azimuth_degrees": 123.30580198912946,
          "distance_au": 206264806247095.9
        },
        {
          "star_name": "Betelgeuse",
          "altitude_degrees": 74.52865857131637,
          "azimuth_degrees": 55.5859062154578,
          "distance_au": 206264806247095.47
        },
        {
          "star_name": "Rigel",
          "altitude_degrees": 82.63857893576127,
          "azimuth_degrees": 159.2775377197831,
          "distance_au": 206264806247095.94
        }
      ],
      "2025-01-14T20:00:00": [
        {
          "star_name": "Sirius",
          "altitude_degrees": 71.56410348640065,
          "azimuth_degrees": 147.51066013820537,
          "distance_au": 206264806247095.9
        },
        {
          "star_name": "Betelgeuse",
          "altitude_degrees": 81.01940156236803,
          "azimuth_degrees": 345.75981873151494,
          "distance_au": 206264806247095.4
        },
        {
          "star_name": "Rigel",
          "altitude_degrees": 75.84843599524335,
          "azimuth_degrees": 240.51459439221853,
          "distance_au": 206264806247095.9
        }
      ],
      "2025-01-14T21:00:00": [
        {
          "star_name": "Sirius",
          "altitude_degrees": 73.83632111032158,
          "azimuth_degrees": 196.81281147118477,
          "distance_au": 206264806247095.9
        },
        {
          "star_name": "Betelgeuse",
          "altitude_degrees": 70.70664565333101,
          "azimuth_degrees": 297.0608683182746,
          "distance_au": 206264806247095.44
        },
        {
          "star_name": "Rigel",
          "altitude_degrees": 61.80276172474408,
          "azimuth_degrees": 254.9955470669125,
          "distance_au": 206264806247095.97
        }
      ],
      "2025-01-14T22:00:00": [
        {
          "star_name": "Sirius",
          "altitude_degrees": 65.07991964640884,
          "azimuth_degrees": 230.5568235892964,
          "distance_au": 206264806247095.94
        }
      ],
      "2025-01-14T23:00:00": [],
      "2025-01-15T00:00:00": [],
      "2025-01-15T01:00:00": []
    }
  },
  "south_america": {
    "region": "south_america",
    "latitude": -23.5505,
    "longitude": -46.6333,
    "star_data_by_hour": {
      "2025-01-14T02:00:00": [
        {
          "star_name": "Sirius",
          "altitude_degrees": 82.03285958131843,
          "azimuth_degrees": 32.10645236101831,
          "distance_au": 206264806247095.88
        },
        {
          "star_name": "Rigel",
          "altitude_degrees": 66.73688068273867,
          "azimuth_degrees": 308.4021247595537,
          "distance_au": 206264806247095.94
        }
      ],
      "2025-01-14T03:00:00": [
        {
          "star_name": "Sirius",
          "altitude_degrees": 77.92843356078164,
          "azimuth_degrees": 302.3729780682391,
          "distance_au": 206264806247095.84
        }
      ],
      "2025-01-14T04:00:00": [
        {
          "star_name": "Sirius",
          "altitude_degrees": 65.00010298371309,
          "azimuth_degrees": 281.01911985579653,
          "distance_au": 206264806247095.94
        }
      ],
      "2025-01-14T05:00:00": [],
      "2025-01-14T06:00:00": [],
      "2025-01-14T07:00:00": [],
      "2025-01-14T08:00:00": [],
      "2025-01-14T09:00:00": [],
      "2025-01-14T10:00:00": [],
      "2025-01-14T11:00:00": [],
      "2025-01-14T12:00:00": [],
      "2025-01-14T13:00:00": [],
      "2025-01-14T14:00:00": [],
      "2025-01-14T15:00:00": [],
      "2025-01-14T16:00:00": [],
      "2025-01-14T17:00:00": [],
      "2025-01-14T18:00:00": [],
      "2025-01-14T19:00:00": [],
      "2025-01-14T20:00:00": [],
      "2025-01-14T21:00:00": [],
      "2025-01-14T22:00:00": [],
      "2025-01-14T23:00:00": [
        {
          "star_name": "Rigel",
          "altitude_degrees": 60.80325825668102,
          "azimuth_degrees": 62.48019785754728,
          "distance_au": 206264806247095.97
        }
      ],
      "2025-01-15T00:00:00": [
        {
          "star_name": "Rigel",
          "altitude_degrees": 71.42476938027316,
          "azimuth_degrees": 35.89165329342481,
          "distance_au": 206264806247095.9
        }
      ],
      "2025-01-15T01:00:00": [
        {
          "star_name": "Sirius",
          "altitude_degrees": 71.39548333947118,
          "azimuth_degrees": 71.95280943583484,
          "distance_au": 206264806247095.9
        },
        {
          "star_name": "Rigel",
          "altitude_degrees": 74.113231024499,
          "azimuth_degrees": 344.7700428287324,
          "distance_au": 206264806247095.97
        }
      ]
    }
  }
}